Workbook

Sheet Resumen ejecutivo
A1: Resumen ejecutivo - alternativas Visual Studio Professional 2026 | B1: Resumen ejecutivo - alternativas Visual Studio Professional 2026 | C1: Resumen ejecutivo - alternativas Visual Studio Professional 2026 | D1: Resumen ejecutivo - alternativas Visual Studio Professional 2026 | E1: Resumen ejecutivo - alternativas Visual Studio Professional 2026 | F1: Resumen ejecutivo - alternativas Visual Studio Professional 2026 | G1: Resumen ejecutivo - alternativas Visual Studio Professional 2026 | H1: Resumen ejecutivo - alternativas Visual Studio Professional 2026
A3: Conclusión | B3: La alternativa recomendada es Estandarización perpetua con SA/LSA: compra SA para 26 licencias perpetuas existentes y compra 4 licencias nuevas retailer LSA para los usuarios actuales en Azure monthly.
A4: Costo 3 años recomendado | B4: ='Alternativas 3 años'!G4 -> 14402.14
A5: Razón | B5: No recompra las 36 licencias perpetuas ya existentes, conserva un modelo objetivo de licencia perpetua con cobertura SA/LSA para migrar a VS 2026, y evita dejar los 4 usuarios en suscripción mensual.
A7: Ranking de alternativas aplicables | B7: Ranking de alternativas aplicables | C7: Ranking de alternativas aplicables | D7: Ranking de alternativas aplicables | E7: Ranking de alternativas aplicables | F7: Ranking de alternativas aplicables | G7: Ranking de alternativas aplicables | H7: Ranking de alternativas aplicables
A9: Ranking | B9: ID | C9: Alternativa | D9: Año 1 USD | E9: Año 2 USD | F9: Año 3 USD | G9: Total 3 años USD | H9: Estado
A10: 1 | B10: A | C10: Estandarización perpetua con SA/LSA | D10: ='Alternativas 3 años'!D4 -> 10428.7 | E10: ='Alternativas 3 años'!E4 -> 2684.4 | F10: ='Alternativas 3 años'!F4 -> 1289.04 | G10: ='Alternativas 3 años'!G4 -> 14402.14 | H10: Recomendado
A11: 2 | B11: B | C11: Todos standalone / IDE independiente | D11: ='Alternativas 3 años'!D5 -> 19960 | E11: ='Alternativas 3 años'!E5 -> 0 | F11: ='Alternativas 3 años'!F5 -> 0 | G11: ='Alternativas 3 años'!G5 -> 19960 | H11: Alternativa con riesgo
A12: 3 | B12: C | C12: Todos Professional Monthly Cloud | D12: ='Alternativas 3 años'!D6 -> 20655 | E12: ='Alternativas 3 años'!E6 -> 20655 | F12: ='Alternativas 3 años'!F6 -> 20655 | G12: ='Alternativas 3 años'!G6 -> 61965 | H12: Alternativa
A13: 4 | B13: D | C13: Todos Professional Standard Subscription anual | D13: ='Alternativas 3 años'!D7 -> 47995.2 | E13: ='Alternativas 3 años'!E7 -> 31963.2 | F13: ='Alternativas 3 años'!F7 -> 31963.2 | G13: ='Alternativas 3 años'!G7 -> 111921.6 | H13: No competitivo

Sheet Inputs
A1: Inputs del modelo | B1: Inputs del modelo | C1: Inputs del modelo | D1: Inputs del modelo
A3: Variable | B3: Valor | C3: Unidad | D3: Notas
A4: Total desarrolladores | B4: 40 | C4: usuarios | D4: Población total del análisis.
A5: Licencias perpetuas existentes sin SA | B5: 26 | C5: usuarios | D5: No se recompran; solo requieren SA para habilitar VS 2026.
A6: Licencias perpetuas existentes con SA vigente | B6: 10 | C6: usuarios | D6: Vencen a finales de este año; no se renuevan porque el alcance actual es VS 2026.
A7: Usuarios actuales en Azure monthly | B7: 4 | C7: usuarios | D7: Únicos usuarios sin licencia perpetua; candidatos a compra nueva.
A8: SA unitario para licencias existentes | B8: 244.19 | C8: USD/año | D8: Aplica solo a las 26 perpetuas existentes sin SA.
A9: Retailer LSA GitHub Year 1 | B9: 1019.94 | C9: USD/usuario | D9: Pago obligatorio según validación del usuario.
A10: Retailer LSA GitHub Year 2 | B10: 671.1 | C10: USD/usuario | D10: Pago obligatorio según validación del usuario.
A11: Retailer LSA GitHub Year 3 | B11: 322.26 | C11: USD/usuario | D11: Pago obligatorio según validación del usuario.
A12: Professional Monthly Cloud | B12: 45 | C12: USD/usuario/mes | D12: Precio publicado por Microsoft.
A13: Descuento monthly desde sexta suscripción | B13: 0.05 | C13: % | D13: Aplica desde la sexta suscripción cloud del mismo tipo.
A14: Usuarios sin descuento monthly | B14: 5 | C14: usuarios | D14: Primeras 5 suscripciones sin descuento.
A15: Professional Standard Subscription año 1 | B15: 99.99 | C15: USD/usuario/mes | D15: Pago anual publicado por Microsoft.
... A18: Horizonte de análisis | B18: 3 | C18: años | D18: Modelo en USD; no incluye impuestos.

Sheet Alternativas 3 años
A1: Alternativas aplicables - horizonte 3 años (USD) | B1: Alternativas aplicables - horizonte 3 años (USD) | C1: Alternativas aplicables - horizonte 3 años (USD) | D1: Alternativas aplicables - horizonte 3 años (USD) | E1: Alternativas aplicables - horizonte 3 años (USD) | F1: Alternativas aplicables - horizonte 3 años (USD) | G1: Alternativas aplicables - horizonte 3 años (USD) | H1: Alternativas aplicables - horizonte 3 años (USD) | I1: Alternativas aplicables - horizonte 3 años (USD) | J1: Alternativas aplicables - horizonte 3 años (USD) | K1: Alternativas aplicables - horizonte 3 años (USD) | L1: Alternativas aplicables - horizonte 3 años (USD)
A3: ID | B3: Alternativa | C3: Modelo objetivo | D3: Año 1 USD | E3: Año 2 USD | F3: Año 3 USD | G3: Total 3 años USD | H3: Tipo de gasto | I3: ¿Derecho perpetuo? | J3: ¿Cobertura actualización? | K3: Riesgo / observación | L3: Estado
A4: A | B4: Estandarización perpetua con SA/LSA | C4: 26 SA sobre licencias existentes + 4 licencias nuevas retailer LSA. Las 10 con SA vigente no se renuevan. | D4: =Inputs!B5*Inputs!B8 + Inputs!B7*Inputs!B9 -> 10428.7 | E4: =Inputs!B7*Inputs!B10 -> 2684.4 | F4: =Inputs!B7*Inputs!B11 -> 1289.04 | G4: =SUM(D4:F4) -> 14402.14 | H4: Mixto | I4: Sí | J4: Sí durante SA activa / LSA | K4: Reutiliza 36 licencias existentes. Evita recomprar para quienes ya tienen perpetua. | L4: Recomendado
A5: B | B5: Todos standalone / IDE independiente | C5: 40 licencias standalone nuevas | D5: =Inputs!B4*Inputs!B17 -> 19960 | E5: 0 | F5: 0 | G5: =SUM(D5:F5) -> 19960 | H5: CAPEX | I5: Sí | J5: No; sin SA | K5: Menor complejidad, pero recompra para 36 usuarios y no conserva ruta clara de SA futura. | L5: Alternativa con riesgo
A6: C | B6: Todos Professional Monthly Cloud | C6: 40 suscripciones mensuales cloud | D6: =((MIN(Inputs!B4,Inputs!B14)*Inputs!B12)+MAX(Inputs!B4-Inputs!B14,0)*Inputs!B12*(1-Inputs!B13))*12 -> 20655 | E6: =((MIN(Inputs!B4,Inputs!B14)*Inputs!B12)+MAX(Inputs!B4-Inputs!B14,0)*Inputs!B12*(1-Inputs!B13))*12 -> 20655 | F6: =((MIN(Inputs!B4,Inputs!B14)*Inputs!B12)+MAX(Inputs!B4-Inputs!B14,0)*Inputs!B12*(1-Inputs!B13))*12 -> 20655 | G6: =SUM(D6:F6) -> 61965 | H6: OPEX | I6: No | J6: Sí mientras se pague | K6: Flexible y cancelable, pero sin derecho perpetuo y más costosa a 3 años que A. | L6: Alternativa
A7: D | B7: Todos Professional Standard Subscription anual | C7: 40 suscripciones Standard anuales | D7: =Inputs!B4*Inputs!B15*12 -> 47995.2 | E7: =Inputs!B4*Inputs!B16*12 -> 31963.2 | F7: =Inputs!B4*Inputs!B16*12 -> 31963.2 | G7: =SUM(D7:F7) -> 111921.6 | H7: OPEX / suscripción anual | I7: Sí, según beneficios Standard | J7: Sí mientras suscripción activa | K7: Más beneficios, pero costo alto. No es Annual Cloud nueva; es Standard Subscription anual. | L7: No competitivo

Sheet Fuentes y supuestos
A1: Fuentes y supuestos | B1: Fuentes y supuestos | C1: Fuentes y supuestos | D1: Fuentes y supuestos | E1: Fuentes y supuestos | F1: Fuentes y supuestos
A3: Tipo | B3: Dato / supuesto | C3: Valor | D3: Fuente / URL | E3: Fecha de consulta | F3: Observación
A4: Fuente Microsoft | B4: Visual Studio Professional monthly | C4: USD 45 usuario/mes | D4: https://visualstudio.microsoft.com/vs/pricing/?tab=paid-subscriptions | E4: 2026-05-27 | F4: Precio oficial usado para escenario Monthly Cloud.
A5: Fuente Microsoft | B5: Visual Studio Professional Standard | C5: USD 99,99 usuario/mes; renovación USD 66,59 | D5: https://visualstudio.microsoft.com/vs/pricing/?tab=paid-subscriptions | E5: 2026-05-27 | F5: Pago anual; escenario de suscripción Standard.
A6: Fuente Microsoft | B6: Visual Studio Professional standalone | C6: USD 499 | D6: https://visualstudio.microsoft.com/vs/pricing/?tab=paid-subscriptions | E6: 2026-05-27 | F6: IDE independiente; sin beneficios de suscripción.
A7: Fuente Microsoft | B7: Software Assurance - New Version Rights | C7: Permite actualizar producto cubierto por SA activa a versión más reciente | D7: https://www.microsoft.com/en-us/licensing/licensing-programs/software-assurance-by-benefits | E7: 2026-05-27 | F7: Soporta uso de SA para habilitar VS 2026.
A8: Validación interna | B8: Elegibilidad 26 licencias perpetuas para adquirir SA | C8: Sí | D8: Confirmación del usuario | E8: 2026-05-27 | F8: SA unitario aplica solo para esas 26 licencias existentes.
A9: Validación interna | B9: Year 1 / Year 2 / Year 3 retailer obligatorios | C9: Sí | D9: Confirmación del usuario | E9: 2026-05-27 | F9: Aplica para licencias nuevas retailer LSA.
A10: Validación interna | B10: No uso de GitHub Enterprise | C10: No se usa | D10: Confirmación del usuario | E10: 2026-05-27 | F10: Reduce valor de negocio del SKU retailer GitHub.
